eecalpy/__init__.py
eecalpy/__main__.py
eecalpy/electrical_units.py
eecalpy/parser.py
eecalpy-0.9.4.dist-info/LICENSE
eecalpy-0.9.4.dist-info/METADATA
eecalpy-0.9.4.dist-info/WHEEL
eecalpy-0.9.4.dist-info/entry_points.txt
eecalpy-0.9.4.dist-info/top_level.txt
eecalpy-0.9.4.dist-info/RECORD
