Metadata-Version: 2.1
Name: eecalpy
Version: 0.9.4
Summary: collection of classes for simple to complex electrical calculations
Home-page: http://github.com/wese3112/eecalpy.git
Author: Sebastian Werner
Author-email: wese3112@startmail.com
License: UNKNOWN
Platform: UNKNOWN
Classifier: Programming Language :: Python :: 3
Classifier: License :: OSI Approved :: GNU General Public License v3 (GPLv3)
Classifier: Operating System :: OS Independent
Requires-Dist: lark-parser
